{
  "CH01": [
    "floor_3_29_tile_31.jpg",
    "floor_3_29_tile_32.jpg",
    "floor_3_29_tile_51.jpg",
    "floor_3_29_tile_52.jpg"
  ],
  "CH02": [
    "floor_3_29_tile_31.jpg",
    "floor_3_29_tile_32.jpg",
    "floor_3_29_tile_51.jpg",
    "floor_3_29_tile_52.jpg"
  ],
  "CH03": [
    "floor_3_29_tile_32.jpg",
    "floor_3_29_tile_33.jpg",
    "floor_3_29_tile_52.jpg",
    "floor_3_29_tile_53.jpg"
  ],
  "CH04": [
    "floor_3_29_tile_32.jpg",
    "floor_3_29_tile_33.jpg",
    "floor_3_29_tile_52.jpg",
    "floor_3_29_tile_53.jpg"
  ],
  "CH05": [
    "floor_3_29_tile_33.jpg",
    "floor_3_29_tile_34.jpg",
    "floor_3_29_tile_53.jpg",
    "floor_3_29_tile_54.jpg"
  ],
  "CH06": [
    "floor_3_29_tile_34.jpg",
    "floor_3_29_tile_35.jpg",
    "floor_3_29_tile_54.jpg",
    "floor_3_29_tile_55.jpg"
  ],
  "CH07": [
    "floor_3_29_tile_34.jpg",
    "floor_3_29_tile_35.jpg",
    "floor_3_29_tile_54.jpg",
    "floor_3_29_tile_55.jpg"
  ],
  "CH08": [
    "floor_3_29_tile_35.jpg",
    "floor_3_29_tile_55.jpg",
    "floor_3_29_tile_56.jpg"
  ],
  "CH09": [
    "floor_3_29_tile_55.jpg",
    "floor_3_29_tile_56.jpg",
    "floor_3_29_tile_75.jpg",
    "floor_3_29_tile_76.jpg"
  ],
  "CH10": [
    "floor_3_29_tile_56.jpg",
    "floor_3_29_tile_57.jpg",
    "floor_3_29_tile_76.jpg",
    "floor_3_29_tile_77.jpg"
  ],
  "CH11": [
    "floor_3_29_tile_56.jpg",
    "floor_3_29_tile_57.jpg",
    "floor_3_29_tile_76.jpg",
    "floor_3_29_tile_77.jpg"
  ],
  "CH12": [
    "floor_3_29_tile_57.jpg",
    "floor_3_29_tile_58.jpg",
    "floor_3_29_tile_77.jpg",
    "floor_3_29_tile_78.jpg"
  ],
  "CH13": [
    "floor_3_29_tile_117.jpg",
    "floor_3_29_tile_96.jpg",
    "floor_3_29_tile_97.jpg"
  ],
  "CH14": [
    "floor_3_29_tile_116.jpg",
    "floor_3_29_tile_117.jpg",
    "floor_3_29_tile_96.jpg",
    "floor_3_29_tile_97.jpg"
  ],
  "CH15": [
    "floor_3_29_tile_115.jpg",
    "floor_3_29_tile_116.jpg",
    "floor_3_29_tile_95.jpg",
    "floor_3_29_tile_96.jpg"
  ],
  "CH16": [
    "floor_3_29_tile_115.jpg",
    "floor_3_29_tile_116.jpg",
    "floor_3_29_tile_95.jpg",
    "floor_3_29_tile_96.jpg"
  ],
  "CH17": [
    "floor_3_29_tile_114.jpg",
    "floor_3_29_tile_115.jpg",
    "floor_3_29_tile_116.jpg",
    "floor_3_29_tile_94.jpg",
    "floor_3_29_tile_95.jpg"
  ],
  "CH18": [
    "floor_3_29_tile_73.jpg",
    "floor_3_29_tile_74.jpg",
    "floor_3_29_tile_93.jpg",
    "floor_3_29_tile_94.jpg"
  ],
  "CH19": [
    "floor_3_29_tile_73.jpg",
    "floor_3_29_tile_74.jpg",
    "floor_3_29_tile_93.jpg",
    "floor_3_29_tile_94.jpg"
  ],
  "CH20": [
    "floor_3_29_tile_73.jpg",
    "floor_3_29_tile_74.jpg",
    "floor_3_29_tile_93.jpg",
    "floor_3_29_tile_94.jpg"
  ],
  "CH21": [
    "floor_3_29_tile_72.jpg",
    "floor_3_29_tile_73.jpg",
    "floor_3_29_tile_92.jpg",
    "floor_3_29_tile_93.jpg"
  ],
  "CH22": [
    "floor_3_29_tile_111.jpg",
    "floor_3_29_tile_112.jpg",
    "floor_3_29_tile_72.jpg",
    "floor_3_29_tile_91.jpg",
    "floor_3_29_tile_92.jpg"
  ],
  "CH23": [
    "floor_3_29_tile_111.jpg",
    "floor_3_29_tile_112.jpg",
    "floor_3_29_tile_91.jpg",
    "floor_3_29_tile_92.jpg"
  ],
  "CH24": [
    "floor_3_29_tile_110.jpg",
    "floor_3_29_tile_111.jpg",
    "floor_3_29_tile_90.jpg",
    "floor_3_29_tile_91.jpg"
  ],
  "CH25": [
    "floor_3_29_tile_110.jpg",
    "floor_3_29_tile_111.jpg",
    "floor_3_29_tile_90.jpg",
    "floor_3_29_tile_91.jpg"
  ],
  "CH26": [
    "floor_3_29_tile_109.jpg",
    "floor_3_29_tile_110.jpg",
    "floor_3_29_tile_89.jpg",
    "floor_3_29_tile_90.jpg"
  ],
  "CH27": [
    "floor_3_29_tile_49.jpg",
    "floor_3_29_tile_50.jpg",
    "floor_3_29_tile_69.jpg",
    "floor_3_29_tile_70.jpg"
  ],
  "CH28": [
    "floor_3_29_tile_49.jpg",
    "floor_3_29_tile_50.jpg",
    "floor_3_29_tile_69.jpg",
    "floor_3_29_tile_70.jpg"
  ],
  "CH29": [
    "floor_3_29_tile_50.jpg",
    "floor_3_29_tile_51.jpg",
    "floor_3_29_tile_70.jpg",
    "floor_3_29_tile_71.jpg"
  ],
  "CH30": [
    "floor_3_29_tile_50.jpg",
    "floor_3_29_tile_51.jpg",
    "floor_3_29_tile_70.jpg",
    "floor_3_29_tile_71.jpg"
  ]
}